lib_x17_datawork-0.1.1.dist-info/licenses/LICENSE
xdatawork/__init__.py
xdatawork/artifact/__init__.py
xdatawork/artifact/artifact.py
xdatawork/artifact/errors.py
xdatawork/artifact/tests/__init__.py
xdatawork/artifact/tests/test_class_artifact_all.py
xdatawork/connect/__init__.py
xdatawork/connect/connectkind.py
xdatawork/connect/connectlike.py
xdatawork/connect/connectref.py
xdatawork/connect/connectreflike.py
xdatawork/connect/errors.py
xdatawork/connect/macos.py
xdatawork/connect/s3.py
xdatawork/connect/tests/__init__.py
xdatawork/connect/tests/test_class_connectkind_all.py
xdatawork/connect/tests/test_class_connectlike_all.py
xdatawork/connect/tests/test_class_connectref_all.py
xdatawork/connect/tests/test_class_connectreflike_all.py
xdatawork/connect/tests/test_class_errors_all.py
xdatawork/connect/tests/test_class_macos_all.py
xdatawork/connect/tests/test_class_s3_all.py
xdatawork/interface/__init__.py
xdatawork/interface/base/__init__.py
xdatawork/interface/base/interface.py
xdatawork/interface/base/partitionkind.py
xdatawork/interface/base/tests/__init__.py
xdatawork/interface/base/tests/test_class_baseinterface_all.py
xdatawork/interface/base/tests/test_class_partitionkind_all.py
xdatawork/interface/factory/__init__.py
xdatawork/interface/factory/error.py
xdatawork/interface/factory/factory.py
xdatawork/interface/factory/tests/__init__.py
xdatawork/interface/factory/tests/test_class_classinterfacefactory_all.py
xdatawork/interface/factory/tests/test_class_errors_all.py
xdatawork/interface/instance/__init__.py
xdatawork/interface/instance/dateptn.py
xdatawork/interface/instance/noneptn.py
xdatawork/interface/instance/snapshotdateptn.py
xdatawork/interface/instance/tests/__init__.py
xdatawork/interface/instance/tests/test_class_dateptn_all.py
xdatawork/interface/instance/tests/test_class_noneptn_all.py
xdatawork/interface/instance/tests/test_class_snapshotdateptn_all.py
xdatawork/serde/__init__.py
xdatawork/serde/format/__init__.py
xdatawork/serde/format/dataformat.py
lib_x17_datawork-0.1.1.dist-info/METADATA
lib_x17_datawork-0.1.1.dist-info/WHEEL
lib_x17_datawork-0.1.1.dist-info/top_level.txt
lib_x17_datawork-0.1.1.dist-info/RECORD
