Metadata-Version: 2.4
Name: lib-x17-datawork
Version: 0.1.1
Summary: Data work library for X17 ecosystem
Author-email: Xing Xing <x.xing.work@gmail.com>
License-Expression: MIT
Requires-Python: >=3.11
License-File: LICENSE
Requires-Dist: pandas
Requires-Dist: pyarrow
Requires-Dist: tomlkit
Provides-Extra: dev
Requires-Dist: pytest>=8.3; extra == "dev"
Requires-Dist: pytest-cov>=6.0; extra == "dev"
Requires-Dist: pytest-benchmark; extra == "dev"
Requires-Dist: ruff>=0.13; extra == "dev"
Requires-Dist: setuptools; extra == "dev"
Requires-Dist: wheel; extra == "dev"
Requires-Dist: twine; extra == "dev"
Requires-Dist: build; extra == "dev"
Provides-Extra: aws
Requires-Dist: boto3; extra == "aws"
Provides-Extra: all
Requires-Dist: boto3; extra == "all"
Dynamic: license-file
